{
    "ships": [
        {
            "name": "Chronspiracy",
            "hp": -10.0,
            "buildings": {
                "engi": [
                    2,
                    0,
                    12
                ],
                "repair": [
                    0,
                    0,
                    4
                ],
                "armor": [
                    0,
                    0,
                    3
                ],
                "light": [
                    0,
                    0,
                    2
                ],
                "medium": [
                    0,
                    0,
                    5
                ],
                "heavy": [
                    0,
                    0,
                    12
                ],
                "shield": [
                    0,
                    0,
                    4
                ],
                "targeting": [
                    0,
                    0,
                    12
                ],
                "munitions": [
                    0,
                    0,
                    15
                ],
                "bridge": [
                    0,
                    12,
                    20
                ],
                "recharge": [
                    0,
                    0,
                    15
                ]
            },
            "shield_time": 1599600510.0274277,
            "shield_charge": 1.0,
            "sunk": true
        },
        {
            "name": "IMPPerium",
            "hp": 50,
            "buildings": {
                "engi": [
                    3,
                    0,
                    24
                ],
                "repair": [
                    0,
                    0,
                    4
                ],
                "armor": [
                    0,
                    0,
                    3
                ],
                "light": [
                    0,
                    0,
                    2
                ],
                "medium": [
                    0,
                    0,
                    5
                ],
                "heavy": [
                    2,
                    0,
                    12
                ],
                "shield": [
                    0,
                    0,
                    4
                ],
                "targeting": [
                    0,
                    0,
                    12
                ],
                "munitions": [
                    0,
                    0,
                    15
                ],
                "bridge": [
                    1,
                    0,
                    20
                ],
                "recharge": [
                    0,
                    0,
                    15
                ]
            },
            "shield_time": 1599600510.0274277,
            "shield_charge": 1.0,
            "sunk": false
        },
        {
            "name": "Eristocracy",
            "hp": -10.0,
            "buildings": {
                "engi": [
                    0,
                    2,
                    3
                ],
                "repair": [
                    0,
                    0,
                    4
                ],
                "armor": [
                    0,
                    0,
                    3
                ],
                "light": [
                    0,
                    0,
                    2
                ],
                "medium": [
                    0,
                    0,
                    5
                ],
                "heavy": [
                    0,
                    1,
                    12
                ],
                "shield": [
                    0,
                    0,
                    4
                ],
                "targeting": [
                    0,
                    0,
                    12
                ],
                "munitions": [
                    0,
                    0,
                    15
                ],
                "bridge": [
                    0,
                    2,
                    20
                ],
                "recharge": [
                    0,
                    0,
                    15
                ]
            },
            "shield_time": 1599600510.0274277,
            "shield_charge": 1.0,
            "sunk": true
        }
    ],
    "last_action": {
        "439605590759702539": 1599677032.3534021,
        "624086807205773343": 1599682552.2787917,
        "537476908166938636": 1599676414.2729523,
        "126435357511122945": 1599660956.0758667,
        "372592544258850816": 1599601275.1291184,
        "598125896049754137": 1599668014.9789834,
        "272902853734170636": 1599669166.0895748,
        "303237993311895553": 1599676957.5904937,
        "329786247545356289": 1599655653.5515056,
        "174993466793787395": 1599676343.5705783,
        "402884012944785409": 1599674392.9789474,
        "486393853448814602": 1599661212.0256734
    },
    "overrides": {
        "537476908166938636": "eristocracy",
        "303237993311895553": "impperium"
    }
}